rpi_gpio_devices/__init__.py
rpi_gpio_devices/base.py
rpi_gpio_devices/button.py
rpi_gpio_devices/fan.py
rpi_gpio_devices/led.py
rpi_gpio_devices/pwmled.py
rpi_gpio_devices/switch.py
rpi_gpio_devices-2.0.1.dist-info/LICENSE
rpi_gpio_devices-2.0.1.dist-info/METADATA
rpi_gpio_devices-2.0.1.dist-info/WHEEL
rpi_gpio_devices-2.0.1.dist-info/top_level.txt
rpi_gpio_devices-2.0.1.dist-info/RECORD
