Metadata-Version: 2.1
Name: rpi-gpio-devices
Version: 2.0.1
Summary: This module provides device classes for controlling the gpio ports
Home-page: https://github.com/danieltodor/rpi-gpio-devices
Author: Daniel Todor
License: MIT
Keywords: Raspberry,Pi,GPIO
Platform: UNKNOWN
Classifier: Development Status :: 5 - Production/Stable
Classifier: Operating System :: POSIX :: Linux
Classifier: License :: OSI Approved :: MIT License
Classifier: Intended Audience :: Developers
Classifier: Programming Language :: Python :: 3.6
Classifier: Programming Language :: Python :: 3.7
Classifier: Programming Language :: Python :: 3.8
Classifier: Programming Language :: Python :: 3.9
Classifier: Programming Language :: Python :: 3.10
Classifier: Programming Language :: Python :: 3.11
Classifier: Topic :: Software Development
Classifier: Topic :: Home Automation
Classifier: Topic :: System :: Hardware
License-File: LICENSE
Requires-Dist: RPi.GPIO (==0.7.1)
